virtui_manager-1.3.0.dist-info/licenses/LICENSE
vmanager/__init__.py
vmanager/config.py
vmanager/connection_manager.py
vmanager/constants.py
vmanager/dialog.css
vmanager/events.py
vmanager/firmware_manager.py
vmanager/i18n.py
vmanager/libvirt_error_handler.py
vmanager/libvirt_utils.py
vmanager/network_manager.py
vmanager/remote_viewer.py
vmanager/remote_viewer_gtk4.py
vmanager/storage_manager.py
vmanager/utils.py
vmanager/virtui_dev.py
vmanager/vm_actions.py
vmanager/vm_cache.py
vmanager/vm_migration.py
vmanager/vm_provisioner.py
vmanager/vm_queries.py
vmanager/vm_service.py
vmanager/vmanager.css
vmanager/vmanager.py
vmanager/vmanager_cmd.py
vmanager/vmcard.css
vmanager/vmcard.py
vmanager/vmcard_pool.py
vmanager/webconsole_manager.py
vmanager/wrapper.py
vmanager/locales/virtui-manager.pot
vmanager/locales/de/LC_MESSAGES/virtui-manager.po
vmanager/locales/fr/LC_MESSAGES/virtui-manager.mo
vmanager/locales/fr/LC_MESSAGES/virtui-manager.po
vmanager/locales/it/LC_MESSAGES/virtui-manager.po
vmanager/modals/__init__.py
vmanager/modals/base_modals.py
vmanager/modals/bulk_modals.py
vmanager/modals/cache_stats_modal.py
vmanager/modals/capabilities_modal.py
vmanager/modals/config_modal.py
vmanager/modals/cpu_mem_pc_modals.py
vmanager/modals/custom_migration_modal.py
vmanager/modals/disk_pool_modals.py
vmanager/modals/host_dashboard_modal.py
vmanager/modals/howto_disk_modal.py
vmanager/modals/howto_network_modal.py
vmanager/modals/howto_overlay_modal.py
vmanager/modals/howto_ssh_modal.py
vmanager/modals/howto_virtiofs_modal.py
vmanager/modals/input_modals.py
vmanager/modals/log_modal.py
vmanager/modals/migration_modals.py
vmanager/modals/network_modals.py
vmanager/modals/provisioning_modals.py
vmanager/modals/select_server_modals.py
vmanager/modals/selection_modals.py
vmanager/modals/server_modals.py
vmanager/modals/server_prefs_modals.py
vmanager/modals/utils_modals.py
vmanager/modals/virsh_modals.py
vmanager/modals/virtiofs_modals.py
vmanager/modals/vm_type_info_modal.py
vmanager/modals/vmanager_modals.py
virtui_manager-1.3.0.dist-info/METADATA
virtui_manager-1.3.0.dist-info/WHEEL
virtui_manager-1.3.0.dist-info/entry_points.txt
virtui_manager-1.3.0.dist-info/top_level.txt
virtui_manager-1.3.0.dist-info/RECORD
