Metadata-Version: 2.4
Name: virtui-manager
Version: 1.3.0
Summary: Terminal-based interface to manage virtual machines using libvirt
Home-page: https://aginies.github.io/virtui-manager/
Author: Antoine Ginies
Author-email: Antoine Ginies <antoine@ginies.org>
Maintainer: Antoine Ginies
Maintainer-email: Antoine Ginies <antoine@ginies.org>
License-Expression: GPL-3.0-or-later
Project-URL: Homepage, https://aginies.github.io/virtui-manager/
Project-URL: Documentation, https://aginies.github.io/virtui-manager/manual
Project-URL: Repository, https://github.com/aginies/virtui-manager
Project-URL: Issues, https://github.com/aginies/virtui-manager/issues
Project-URL: Changelog, https://github.com/aginies/virtui-manager/releases
Keywords: virtualization,libvirt,kvm,qemu,tui,terminal,manager,virt
Classifier: Development Status :: 4 - Beta
Classifier: Environment :: Console
Classifier: Intended Audience :: System Administrators
Classifier: Operating System :: POSIX :: Linux
Classifier: Programming Language :: Python :: 3
Classifier: Programming Language :: Python :: 3.7
Classifier: Programming Language :: Python :: 3.8
Classifier: Programming Language :: Python :: 3.9
Classifier: Programming Language :: Python :: 3.10
Classifier: Programming Language :: Python :: 3.11
Classifier: Programming Language :: Python :: 3.12
Classifier: Programming Language :: Python :: 3.13
Classifier: Topic :: System :: Systems Administration
Classifier: Topic :: Utilities
Requires-Python: >=3.6
License-File: LICENSE
Requires-Dist: libvirt-python>=6.0.0
Requires-Dist: textual>=0.40.0
Requires-Dist: PyYAML>=5.4.0
Requires-Dist: markdown-it-py>=3.0.0
Provides-Extra: dev
Requires-Dist: pytest>=7.0.0; extra == "dev"
Requires-Dist: pytest-cov>=4.0.0; extra == "dev"
Requires-Dist: black>=23.0.0; extra == "dev"
Requires-Dist: ruff>=0.1.0; extra == "dev"
Requires-Dist: mypy>=1.0.0; extra == "dev"
Provides-Extra: webconsole
Requires-Dist: websockify>=0.10.0; extra == "webconsole"
Dynamic: license-file
